utnamtte/__init__.py
utnamtte-0.0.2.dist-info/LICENCE.txt
utnamtte-0.0.2.dist-info/METADATA
utnamtte-0.0.2.dist-info/WHEEL
utnamtte-0.0.2.dist-info/top_level.txt
utnamtte-0.0.2.dist-info/RECORD
