Metadata-Version: 2.1
Name: utnamtte
Version: 0.0.2
Summary: A better eval function, eg 2π = 2*math.pi
Home-page: https://github.com/utkarsh-naman/MATEX
Author: Utkarsh Naman
Author-email: its.utnam@gmail.com
License: MIT
Keywords: tte eval calculator text-to-expression utnamtte
Platform: UNKNOWN
Classifier: Development Status :: 5 - Production/Stable
Classifier: Intended Audience :: Education
Classifier: Operating System :: POSIX :: Linux
Classifier: License :: OSI Approved :: MIT License
Classifier: Programming Language :: Python :: 2.7
Classifier: Programming Language :: Python :: 3
License-File: LICENCE.txt
